{"classes": ["COLOR", "TYPE"], "annotations": [["There were 10 red lightbulb with rainbow lights around the edges", {"entities": [[14, 17, "COLOR"], [18, 23, "TYPE"], [18, 27, "TYPE"], [33, 40, "COLOR"]]}], ["There were 10 red dot with rainbow lights around the edges", {"entities": [[14, 17, "COLOR"], [18, 21, "TYPE"], [27, 34, "COLOR"]]}], ["There were 10 purple pyramid with pink lights around the edges", {"entities": [[14, 20, "COLOR"], [21, 28, "TYPE"], [34, 38, "COLOR"]]}], ["There were 10 red dome with rainbow lights around the edges", {"entities": [[14, 17, "COLOR"], [18, 22, "TYPE"], [28, 35, "COLOR"]]}], ["There were 10 green pyramid with orange lights around the edges", {"entities": [[14, 19, "COLOR"], [20, 27, "TYPE"], [33, 39, "COLOR"]]}]]}