{"classes": ["COLOR", "TYPE"], "annotations": [["There were 10 blue rod with yellow lights around the edges", {"entities": [[14, 18, "COLOR"], [19, 22, "TYPE"], [28, 34, "COLOR"]]}], ["There were 10 white crescent with gray lights around the edges", {"entities": [[14, 19, "COLOR"], [20, 28, "TYPE"], [34, 38, "COLOR"]]}], ["There were 10 blue flying disk with yellow lights around the edges", {"entities": [[14, 18, "COLOR"], [19, 30, "TYPE"], [26, 30, "TYPE"], [36, 42, "COLOR"]]}], ["There were 10 orange rectangle with grey lights around the edges", {"entities": [[14, 20, "COLOR"], [21, 30, "TYPE"], [36, 40, "COLOR"]]}], ["There were 10 purple wing with pink lights around the edges", {"entities": [[14, 20, "COLOR"], [21, 25, "TYPE"], [31, 35, "COLOR"]]}]]}