{"classes": ["COLOR", "TYPE"], "annotations": [["I saw what looked like a diamond hovering silently", {"entities": [[25, 32, "TYPE"]]}], ["I saw what looked like a tic tac hovering silently", {"entities": [[25, 32, "TYPE"]]}], ["I saw what looked like a trapezoid hovering silently", {"entities": [[25, 34, "TYPE"]]}], ["I saw what looked like a boomerang hovering silently", {"entities": [[25, 34, "TYPE"]]}], ["I saw what looked like a lightbulb hovering silently", {"entities": [[25, 30, "TYPE"], [25, 34, "TYPE"]]}]]}